cbr_web_components/__init__.py
cbr_web_components/html/webc-dev.html
cbr_web_components/html/webc.html
cbr_web_components/js/cbr/CBR_Events.mjs
cbr_web_components/js/cbr/CBR__Paths.mjs
cbr_web_components/js/cbr/api/API__Chat_Bot.mjs
cbr_web_components/js/cbr/api/API__Markdown.mjs
cbr_web_components/js/cbr/api/API__User_Data__Files.mjs
cbr_web_components/js/cbr/api/API__Web__Forms.mjs
cbr_web_components/js/cbr/document-assistant/WebC__Document__Assistant.mjs
cbr_web_components/js/cbr/document-assistant/WebC__Document__Chat.mjs
cbr_web_components/js/cbr/document-assistant/WebC__Document__Diff.mjs
cbr_web_components/js/cbr/document-assistant/WebC__Document__Editor.mjs
cbr_web_components/js/cbr/elements/CBR__Content__Placeholder.mjs
cbr_web_components/js/cbr/elements/CBR__Left_Footer.mjs
cbr_web_components/js/cbr/elements/CBR__Top_Banner.mjs
cbr_web_components/js/cbr/file-system/WebC__User_Files.mjs
cbr_web_components/js/cbr/file-system/WebC__User_Files__Actions.mjs
cbr_web_components/js/cbr/file-system/WebC__User_Files__Content__Chat.mjs
cbr_web_components/js/cbr/file-system/WebC__User_Files__File_Viewer.mjs
cbr_web_components/js/cbr/file-system/WebC__User_Files__Folder_Viewer.mjs
cbr_web_components/js/cbr/file-system/WebC__User_Files__Tree_View.mjs
cbr_web_components/js/cbr/file-system/WebC__User_Files__Upload.mjs
cbr_web_components/js/cbr/llms/LLM__Handler.mjs
cbr_web_components/js/cbr/llms/LLM__Response__Handler.mjs
cbr_web_components/js/cbr/llms/WebC__LLM__Test.mjs
cbr_web_components/js/cbr/main-page/CBR__Important_Alert.mjs
cbr_web_components/js/cbr/main-page/CBR__Left_Logo.mjs
cbr_web_components/js/cbr/main-page/CSS__CBR__Layout__Default.mjs
cbr_web_components/js/cbr/main-page/WebC__CBR__Left_Menu.mjs
cbr_web_components/js/cbr/main-page/WebC__CBR__Main_Page.mjs
cbr_web_components/js/cbr/main-page/WebC__CBR__Top_Banner.mjs
cbr_web_components/js/cbr/markdown-editor/WebC__User_Files__Markdown.mjs
cbr_web_components-0.12.137.dist-info/LICENSE
cbr_web_components-0.12.137.dist-info/METADATA
cbr_web_components-0.12.137.dist-info/WHEEL
cbr_web_components-0.12.137.dist-info/RECORD
