Metadata-Version: 2.1
Name: cbr_web_components
Version: 0.12.137
Summary: CBR - Web Components
Home-page: https://github.com/the-cyber-boardroom/cbr-web-components
License: MIT
Author: Dinis Cruz
Author-email: dinis.cruz@owasp.org
Requires-Python: >=3.7,<4.0
Classifier: License :: OSI Approved :: MIT License
Classifier: Programming Language :: Python :: 3
Classifier: Programming Language :: Python :: 3.7
Classifier: Programming Language :: Python :: 3.8
Classifier: Programming Language :: Python :: 3.9
Classifier: Programming Language :: Python :: 3.10
Classifier: Programming Language :: Python :: 3.11
Classifier: Programming Language :: Python :: 3.12
Classifier: Programming Language :: Python :: 3.13
Requires-Dist: osbot-utils
Project-URL: Repository, https://github.com/the-cyber-boardroom/cbr-web-components
